ddddocr/__init__.py
ddddocr/__main__.py
ddddocr/common.onnx
ddddocr/common_det.onnx
ddddocr/common_old.onnx
ddddocr/api/__init__.py
ddddocr/api/mcp.py
ddddocr/api/models.py
ddddocr/api/routes.py
ddddocr/api/server.py
ddddocr/compat/__init__.py
ddddocr/compat/legacy.py
ddddocr/core/__init__.py
ddddocr/core/base.py
ddddocr/core/detection_engine.py
ddddocr/core/ocr_engine.py
ddddocr/core/slide_engine.py
ddddocr/models/__init__.py
ddddocr/models/charset_manager.py
ddddocr/models/model_loader.py
ddddocr/preprocessing/__init__.py
ddddocr/preprocessing/color_filter.py
ddddocr/preprocessing/image_processor.py
ddddocr/utils/__init__.py
ddddocr/utils/exceptions.py
ddddocr/utils/image_io.py
ddddocr/utils/validators.py
ddddocr_unofficial-1.6.0.dist-info/licenses/LICENSE
ddddocr_unofficial-1.6.0.dist-info/METADATA
ddddocr_unofficial-1.6.0.dist-info/WHEEL
ddddocr_unofficial-1.6.0.dist-info/entry_points.txt
ddddocr_unofficial-1.6.0.dist-info/top_level.txt
ddddocr_unofficial-1.6.0.dist-info/RECORD
