Metadata-Version: 2.4
Name: ddddocr-unofficial
Version: 1.6.0
Summary: Unofficial PyPI release of ddddocr v1.6.0. This package provides an up-to-date, installable version of the original work by sml2h3.
Home-page: https://github.com/sml2h3/ddddocr
Author: sml2h3 (Original Author)
License: MIT
Project-URL: Homepage, https://github.com/sml2h3/ddddocr
Project-URL: Repository, https://github.com/sml2h3/ddddocr
Project-URL: Bug Tracker, https://github.com/sml2h3/ddddocr/issues
Keywords: ocr,ddddocr,captcha
Classifier: License :: OSI Approved :: MIT License
Classifier: Operating System :: OS Independent
Classifier: Programming Language :: Python :: 3
Classifier: Programming Language :: Python :: 3.7
Classifier: Programming Language :: Python :: 3.8
Classifier: Programming Language :: Python :: 3.9
Classifier: Programming Language :: Python :: 3.10
Classifier: Programming Language :: Python :: 3.11
Classifier: Programming Language :: Python :: 3.12
Classifier: Topic :: Scientific/Engineering :: Image Recognition
Requires-Python: <=3.13
License-File: LICENSE
Requires-Dist: numpy
Requires-Dist: onnxruntime
Requires-Dist: Pillow
Requires-Dist: opencv-python-headless
Provides-Extra: api
Requires-Dist: fastapi>=0.100.0; extra == "api"
Requires-Dist: uvicorn[standard]>=0.20.0; extra == "api"
Requires-Dist: pydantic>=2.0.0; extra == "api"
Dynamic: home-page
Dynamic: license-file
Dynamic: requires-python
